docling_langchain/__init__.py
docling_langchain/loader.py
docling_langchain/py.typed
docling_langchain-0.1.0.dist-info/LICENSE
docling_langchain-0.1.0.dist-info/METADATA
docling_langchain-0.1.0.dist-info/WHEEL
docling_langchain-0.1.0.dist-info/RECORD
