Metadata-Version: 2.1
Name: docling-langchain
Version: 0.1.0
Summary: Docling LangChain integration
Home-page: https://github.com/DS4SD/docling-langchain
License: MIT
Author: Panos Vagenas
Author-email: pva@zurich.ibm.com
Requires-Python: >=3.9,<3.13
Classifier: Development Status :: 5 - Production/Stable
Classifier: Intended Audience :: Developers
Classifier: Intended Audience :: Science/Research
Classifier: License :: OSI Approved :: MIT License
Classifier: Operating System :: MacOS :: MacOS X
Classifier: Operating System :: POSIX :: Linux
Classifier: Programming Language :: Python :: 3
Classifier: Programming Language :: Python :: 3.9
Classifier: Programming Language :: Python :: 3.10
Classifier: Programming Language :: Python :: 3.11
Classifier: Programming Language :: Python :: 3.12
Classifier: Topic :: Scientific/Engineering :: Artificial Intelligence
Requires-Dist: docling (>=2.14.0,<3.0.0)
Requires-Dist: langchain-core (>=0.3.0,<0.4.0)
Project-URL: Repository, https://github.com/DS4SD/docling-langchain
